realesrgan/__init__.py
realesrgan/compatibility.py
realesrgan/numpy_compatibility.py
realesrgan/post_install.py
realesrgan/train.py
realesrgan/utils.py
realesrgan/version.py
realesrgan/archs/__init__.py
realesrgan/archs/discriminator_arch.py
realesrgan/archs/srvgg_arch.py
realesrgan/data/__init__.py
realesrgan/data/degradations.py
realesrgan/data/realesrgan_dataset.py
realesrgan/data/realesrgan_paired_dataset.py
realesrgan/models/__init__.py
realesrgan/models/realesrgan_model.py
realesrgan/models/realesrnet_model.py
realesrgan_enhanced-0.4.5.dist-info/licenses/LICENSE
realesrgan_enhanced-0.4.5.dist-info/METADATA
realesrgan_enhanced-0.4.5.dist-info/WHEEL
realesrgan_enhanced-0.4.5.dist-info/entry_points.txt
realesrgan_enhanced-0.4.5.dist-info/top_level.txt
realesrgan_enhanced-0.4.5.dist-info/RECORD
