Metadata-Version: 2.4
Name: realesrgan-enhanced
Version: 0.4.5
Summary: Real-ESRGAN aims at developing Practical Algorithms for General Image Restoration
Home-page: https://github.com/xinntao/Real-ESRGAN
Author: Xintao Wang
Author-email: Xintao Wang <xintao.wang@outlook.com>
License-Expression: BSD-3-Clause
Project-URL: Homepage, https://github.com/xinntao/Real-ESRGAN
Project-URL: Repository, https://github.com/xinntao/Real-ESRGAN
Project-URL: Documentation, https://github.com/xinntao/Real-ESRGAN/blob/master/README.md
Project-URL: Bug Tracker, https://github.com/xinntao/Real-ESRGAN/issues
Keywords: computer vision,pytorch,image restoration,super-resolution,esrgan,real-esrgan
Classifier: Development Status :: 4 - Beta
Classifier: Operating System :: OS Independent
Classifier: Programming Language :: Python :: 3
Classifier: Programming Language :: Python :: 3.8
Classifier: Programming Language :: Python :: 3.9
Classifier: Programming Language :: Python :: 3.10
Classifier: Programming Language :: Python :: 3.11
Classifier: Programming Language :: Python :: 3.12
Classifier: Topic :: Scientific/Engineering :: Artificial Intelligence
Classifier: Topic :: Scientific/Engineering :: Image Processing
Requires-Python: >=3.8
License-File: LICENSE
Requires-Dist: basicsr>=1.4.2
Requires-Dist: facexlib>=0.2.5
Requires-Dist: gfpgan>=1.3.5
Requires-Dist: numpy>=2.0.0
Requires-Dist: opencv-python>=4.8.0
Requires-Dist: Pillow>=10.0.1
Requires-Dist: torch>=1.7.0
Requires-Dist: torchvision>=0.8.0
Requires-Dist: tqdm>=4.60.0
Provides-Extra: dev
Requires-Dist: pytest>=6.0; extra == "dev"
Requires-Dist: flake8>=3.8.0; extra == "dev"
Requires-Dist: yapf>=0.30.0; extra == "dev"
Requires-Dist: isort>=5.0.0; extra == "dev"
Requires-Dist: pre-commit>=2.0.0; extra == "dev"
Provides-Extra: test
Requires-Dist: pytest>=6.0; extra == "test"
Requires-Dist: pytest-cov>=2.0; extra == "test"
Dynamic: author
Dynamic: home-page
Dynamic: license-file
